catwalk/__init__.py
catwalk/__main__.py
catwalk/utils.py
catwalk/cicd/__init__.py
catwalk/cicd/base_test.py
catwalk/cicd/build_steps.py
catwalk/cicd/deploy.py
catwalk/cicd/test_image.py
catwalk/cicd/test_model.py
catwalk/cicd/test_server.py
catwalk/cryptography/__init__.py
catwalk/cryptography/aesgcm.py
catwalk/helpers/__init__.py
catwalk/helpers/configuration.py
catwalk/helpers/logging.py
catwalk/server/__init__.py
catwalk/server/app.py
catwalk/server/nginx.py
catwalk/server/serve.py
catwalk/templates/Dockerfile.j2
catwalk/templates/docker-compose.yml.j2
catwalk/templates/dockerignore.j2
catwalk/templates/nginx-https.conf.j2
catwalk/templates/nginx.conf.j2
catwalk/templates/wsgi.py.j2
catwalk/validation/__init__.py
catwalk/validation/model.py
catwalk/validation/schema.py
tests/__init__.py
tests/test_build_prep.py
tests/test_config.py
tests/test_cryptography.py
tests/test_deploy_prep.py
tests/test_examples.py
tests/test_logging.py
tests/test_utils.py
lb_catwalk-0.1.0.dist-info/LICENSE
lb_catwalk-0.1.0.dist-info/METADATA
lb_catwalk-0.1.0.dist-info/NOTICE
lb_catwalk-0.1.0.dist-info/WHEEL
lb_catwalk-0.1.0.dist-info/entry_points.txt
lb_catwalk-0.1.0.dist-info/top_level.txt
lb_catwalk-0.1.0.dist-info/RECORD
