Metadata-Version: 2.1
Name: lb-catwalk
Version: 0.1.0
Summary: UNKNOWN
Home-page: UNKNOWN
Author: UNKNOWN
Author-email: UNKNOWN
License: UNKNOWN
Platform: UNKNOWN
Requires-Dist: click
Requires-Dist: cryptography
Requires-Dist: docker
Requires-Dist: Flask
Requires-Dist: gunicorn
Requires-Dist: gevent
Requires-Dist: PyYAML
Requires-Dist: schema
